neethuantony/__init__.py
neethuantony/view.py
installneethu-1.0.0.dist-info/METADATA
installneethu-1.0.0.dist-info/WHEEL
installneethu-1.0.0.dist-info/entry_points.txt
installneethu-1.0.0.dist-info/top_level.txt
installneethu-1.0.0.dist-info/RECORD
